ymodterm/__init__.py
ymodterm/__main__.py
ymodterm-0.1.0b3.dist-info/licenses/LICENSE
ymodterm-0.1.0b3.dist-info/METADATA
ymodterm-0.1.0b3.dist-info/WHEEL
ymodterm-0.1.0b3.dist-info/entry_points.txt
ymodterm-0.1.0b3.dist-info/top_level.txt
ymodterm-0.1.0b3.dist-info/RECORD
