Metadata-Version: 2.4
Name: ymodterm
Version: 0.1.0b3
Summary: Serial terminal with Y-Modem transfer support
Author: o-murphy
License: Copyright 2025 Dmytro Yaroshenko
Project-URL: Homepage, https://github.com/o-murphy/ymodterm
Project-URL: Bug Reports, https://github.com/o-murphy/ymodterm/issues
Project-URL: Source, https://github.com/o-murphy/ymodterm
Keywords: serial,uart,ymodem,xmodem
Classifier: Intended Audience :: Developers
Classifier: Natural Language :: English
Classifier: Programming Language :: Python
Classifier: Topic :: Software Development :: Libraries :: Python Modules
Classifier: Programming Language :: Python :: 3
Classifier: Programming Language :: Python :: 3 :: Only
Classifier: Programming Language :: Python :: 3.10
Classifier: Programming Language :: Python :: 3.11
Classifier: Programming Language :: Python :: 3.12
Classifier: Programming Language :: Python :: 3.13
Classifier: Programming Language :: Python :: 3.14
Classifier: Programming Language :: Python :: Implementation :: CPython
Requires-Python: >=3.10
License-File: LICENSE
Requires-Dist: pyside6>=6.10.1
Requires-Dist: qtpy>=2.4.3
Requires-Dist: ymodem>=1.5.3
Dynamic: license-file
